MANIFEST.in
README.rst
setup.cfg
setup.py
sendsay/__init__.py
sendsay/api.py
sendsay/exceptions.py
sendsay/version.py
sendsay_api_python.egg-info/PKG-INFO
sendsay_api_python.egg-info/SOURCES.txt
sendsay_api_python.egg-info/dependency_links.txt
sendsay_api_python.egg-info/requires.txt
sendsay_api_python.egg-info/top_level.txt
test/__init__.py
test/test_sendsay.py
test/data/img.png
test/data/test_attach_file.json
test/data/test_track_wait.json