Metadata-Version: 1.1
Name: sendsay-api-python
Version: 0.1.4
Summary: The Sendsay API client library.
Home-page: https://github.com/sendsay-ru/sendsay-api-python
Author: Vadim Khakulov
Author-email: vadim.khakulov@gmail.com
License: Apache
Platform: UNKNOWN
Classifier: License :: OSI Approved :: Apache Software License
Classifier: Programming Language :: Python
Classifier: Programming Language :: Python :: 2.6
Classifier: Programming Language :: Python :: 2.7
Classifier: Programming Language :: Python :: 3
Classifier: Programming Language :: Python :: 3.3
Classifier: Programming Language :: Python :: 3.4
Classifier: Programming Language :: Python :: 3.5
